exovetter/__init__.py
exovetter/const.py
exovetter/leo.py
exovetter/lightkurve_utils.py
exovetter/lpp.py
exovetter/model.py
exovetter/odd_even.py
exovetter/sweet.py
exovetter/tce.py
exovetter/transit_coverage.py
exovetter/trapezoid_fit.py
exovetter/utils.py
exovetter/version.py
exovetter/vetters.py
exovetter/viz_transits.py
exovetter/centroid/__init__.py
exovetter/centroid/centroid.py
exovetter/centroid/covar.py
exovetter/centroid/disp.py
exovetter/centroid/fastpsffit.py
exovetter/modshift/__init__.py
exovetter/modshift/modshift.py
exovetter/modshift/plotmodshift.py
exovetter-0.0.10.dist-info/LICENSE.rst
exovetter-0.0.10.dist-info/METADATA
exovetter-0.0.10.dist-info/WHEEL
exovetter-0.0.10.dist-info/top_level.txt
exovetter-0.0.10.dist-info/RECORD
