Metadata-Version: 2.1
Name: exovetter
Version: 0.0.10
Summary: Exoplanet vetting package
Home-page: https://github.com/spacetelescope/exovetter
Author: Susan Mullally et al.
Author-email: smullally@stsci.edu
License: BSD 3-Clause
Requires-Python: >=3.7
License-File: LICENSE.rst
Requires-Dist: numpy
Requires-Dist: astropy>=3
Requires-Dist: scipy
Provides-Extra: all
Requires-Dist: matplotlib; extra == "all"
Requires-Dist: scikit-learn; extra == "all"
Requires-Dist: lightkurve>=2; extra == "all"
Requires-Dist: lpproj; extra == "all"
Provides-Extra: docs
Requires-Dist: sphinx-astropy; extra == "docs"
Requires-Dist: sphinx-rtd-theme; extra == "docs"
Provides-Extra: test
Requires-Dist: pytest-cov; extra == "test"
Requires-Dist: pytest-remotedata; extra == "test"
Requires-Dist: pytest-doctestplus; extra == "test"
Requires-Dist: oktopus; extra == "test"
Requires-Dist: autograd; extra == "test"
